dimworks/__init__.py
dimworks/stat.py
dimworks-0.0.4.dist-info/License
dimworks-0.0.4.dist-info/METADATA
dimworks-0.0.4.dist-info/WHEEL
dimworks-0.0.4.dist-info/top_level.txt
dimworks-0.0.4.dist-info/RECORD
