Metadata-Version: 2.1
Name: dimworks
Version: 0.0.4
Summary: Calculate statics for manufacturing quality control
Home-page: https://github.com/guishengwang/QCPy
Author: Guisheng Wang
Author-email: guisheng.wang66@gmail.com
License: UNKNOWN
Platform: UNKNOWN
Classifier: Programming Language :: Python :: 3
Classifier: License :: OSI Approved :: MIT License
Classifier: Operating System :: OS Independent
Requires-Python: >=3.6
